example1.py
example2.py
example3.py
pygame_light2d/__init__.py
pygame_light2d/double_buff.py
pygame_light2d/engine.py
pygame_light2d/fragment_blur.glsl
pygame_light2d/fragment_light.glsl
pygame_light2d/fragment_mask.glsl
pygame_light2d/hull.py
pygame_light2d/light.py
pygame_light2d/vertex.glsl
pygame_light2d-2.1.3.dist-info/licenses/LICENSE
pygame_light2d-2.1.3.dist-info/METADATA
pygame_light2d-2.1.3.dist-info/WHEEL
pygame_light2d-2.1.3.dist-info/top_level.txt
pygame_light2d-2.1.3.dist-info/RECORD
