Metadata-Version: 2.4
Name: pygame-light2d
Version: 2.1.3
Summary: Fast 2D dynamic lighting engine for Pygame.
Author: Markel Zubia
License: MIT License
Project-URL: Homepage, https://github.com/MarkelZ/pygame-light2d
Project-URL: Documentation, https://github.com/MarkelZ/pygame-light2d/wiki
Project-URL: Bug Reports, https://github.com/MarkelZ/pygame-light2d/issues
Keywords: pygame,light,lights,engine,shadows,dynamic,2D
Classifier: License :: OSI Approved :: MIT License
Classifier: Programming Language :: Python
Classifier: Programming Language :: Python :: 3
Requires-Python: >=3.10
License-File: LICENSE
Requires-Dist: numpy>=1.24.1
Requires-Dist: moderngl>=5.8.2
Requires-Dist: PyOpenGL>=3.1.6
Requires-Dist: pygame-render>=1.3.0
Dynamic: license-file
